degenerate_dna/__init__.py
degenerate_dna/_warnings.py
degenerate_dna/api.py
degenerate_dna/exceptions.py
degenerate_dna/tables.py
degenerate_dna-0.1.2.dist-info/licenses/LICENSE
tests/__init__.py
tests/test_degenerate_dna.py
degenerate_dna-0.1.2.dist-info/METADATA
degenerate_dna-0.1.2.dist-info/WHEEL
degenerate_dna-0.1.2.dist-info/top_level.txt
degenerate_dna-0.1.2.dist-info/RECORD
