Metadata-Version: 2.4
Name: degenerate-dna
Version: 0.1.2
Summary: Python implementation of the Degen Perl package by Zwick et al.
Home-page: https://github.com/carlosp420/degenerate-dna
Author: Carlos Pena
Author-email: mycalesis@gmail.com
License: BSD-3-Clause
Classifier: Development Status :: 5 - Production/Stable
Classifier: Programming Language :: Python
Classifier: Programming Language :: Python :: 3.10
Classifier: Programming Language :: Python :: 3.11
Classifier: Programming Language :: Python :: 3.12
License-File: LICENSE
Dynamic: author
Dynamic: author-email
Dynamic: classifier
Dynamic: description
Dynamic: home-page
Dynamic: license
Dynamic: license-file
Dynamic: summary
